cli/__init__.py
cli/kmk.py
core/__init__.py
kafka_mirror_kit-0.1.0.dist-info/LICENSE
kafka_mirror_kit-0.1.0.dist-info/METADATA
kafka_mirror_kit-0.1.0.dist-info/WHEEL
kafka_mirror_kit-0.1.0.dist-info/entry_points.txt
kafka_mirror_kit-0.1.0.dist-info/top_level.txt
kafka_mirror_kit-0.1.0.dist-info/RECORD
