Metadata-Version: 2.1
Name: kafka-mirror-kit
Version: 0.1.0
Summary: to deploy and orchestrate geo-replicated Apache Kafka clusters using Apache MirrorMaker 2.
Author-email: Gianluigi De Marco <dem.gianluigi@gmail.com>
License: 
Project-URL: Homepage, https://github.com/dmgiangi/kafka-mirror-kit
Project-URL: Bug Tracker, https://github.com/dmgiangi/kafka-mirror-kit/issues
Keywords: kafka,mirrorMaker2,python
Classifier: Development Status :: 3 - Alpha
Classifier: Intended Audience :: Developers
Classifier: License :: OSI Approved :: Apache Software License
Classifier: Programming Language :: Python :: 3
Classifier: Programming Language :: Python :: 3.8
Classifier: Programming Language :: Python :: 3.9
Classifier: Programming Language :: Python :: 3.10
Classifier: Programming Language :: Python :: 3.11
Classifier: Programming Language :: Python :: 3.12
Classifier: Operating System :: OS Independent
Classifier: Topic :: Software Development :: Libraries :: Python Modules
Requires-Python: >=3.8
License-File: LICENSE
Requires-Dist: click>=8.0.0
Requires-Dist: kafka-python>=2.0.0
Requires-Dist: pytest>=7.0.0
